LICENSE
MANIFEST.in
README.md
README.rst
setup.py
cdn_assets/__init__.py
cdn_assets.egg-info/PKG-INFO
cdn_assets.egg-info/SOURCES.txt
cdn_assets.egg-info/dependency_links.txt
cdn_assets.egg-info/requires.txt
cdn_assets.egg-info/top_level.txt
cdn_assets/management/__init__.py
cdn_assets/management/commands/__init__.py
cdn_assets/management/commands/download.py
cdn_assets/templatetags/__init__.py
cdn_assets/templatetags/cdn_assets.py