Metadata-Version: 1.1
Name: cdn-assets
Version: 0.2.3
Summary: Using CDN Assets(mainly JS and css) instead of downloading asset by your self.
Home-page: https://github.com/lsc20051426/cdn-asserts
Author: L
Author-email: lsc20051426@163.com
License: BSD License
Platform: UNKNOWN
Classifier: Environment :: Web Environment
Classifier: Framework :: Django
Classifier: Framework :: Django :: 1.8
Classifier: Intended Audience :: Developers
Classifier: License :: OSI Approved :: BSD License
Classifier: Operating System :: OS Independent
Classifier: Programming Language :: Python
Classifier: Topic :: Internet :: WWW/HTTP
Classifier: Topic :: Internet :: WWW/HTTP :: Dynamic Content
